hammett/__init__.py
hammett/__main__.py
hammett/colors.py
hammett/fixtures.py
hammett/fixtures_support.py
hammett/impl.py
hammett/mark.py
hammett-0.9.2.dist-info/AUTHORS.rst
hammett-0.9.2.dist-info/LICENSE
hammett-0.9.2.dist-info/METADATA
hammett-0.9.2.dist-info/WHEEL
hammett-0.9.2.dist-info/entry_points.txt
hammett-0.9.2.dist-info/top_level.txt
hammett-0.9.2.dist-info/RECORD
