Metadata-Version: 2.1
Name: hammett
Version: 0.9.2
Summary: hammett is a fast python test runner
Home-page: https://github.com/boxed/hammett
Author: Anders Hovmöller
Author-email: boxed@killingar.net
License: BSD
Keywords: hammett
Platform: UNKNOWN
Classifier: Development Status :: 3 - Alpha
Classifier: Intended Audience :: Developers
Classifier: License :: OSI Approved :: BSD License
Classifier: Natural Language :: English
Classifier: Programming Language :: Python :: 3
Classifier: Programming Language :: Python :: 3.6
Classifier: Programming Language :: Python :: 3.7
Classifier: Programming Language :: Python :: 3.8
Requires-Dist: astunparse
